btree_index/__init__.py
btree_index/base.py
btree_index/b_tree_policy/__init__.py
btree_index/b_tree_policy/b_plus_tree.py
btree_index/b_tree_policy/b_tree_printer.py
btree_index-0.1.0.dist-info/LICENSE
btree_index-0.1.0.dist-info/METADATA
btree_index-0.1.0.dist-info/WHEEL
btree_index-0.1.0.dist-info/top_level.txt
btree_index-0.1.0.dist-info/RECORD
