Metadata-Version: 2.1
Name: btree-index
Version: 0.1.0
Summary: Python package for implementing a B-Tree
Home-page: https://github.com/diomandeee/btree_index
Author: Mohamed Diomande
Author-email: gdiomande7907@gmail.com
License: MIT
Classifier: Programming Language :: Python :: 3
Classifier: License :: OSI Approved :: MIT License
Classifier: Operating System :: OS Independent
Requires-Python: >=3.6
License-File: LICENSE
Requires-Dist: numpy
Requires-Dist: scipy
